meli_package/__init__.py
meli_package/attributes.py
meli_package/authentication.py
meli_package/categories.py
meli_package/currency.py
meli_package/itens.py
meli_package/local.py
meli_package/metrics.py
meli_package/opinions.py
meli_package/orders.py
meli_package/posts.py
meli_package/questions.py
meli_package/shipping.py
meli_package/user_info.py
meli_package-0.0.7.dist-info/LICENSE
meli_package-0.0.7.dist-info/METADATA
meli_package-0.0.7.dist-info/WHEEL
meli_package-0.0.7.dist-info/top_level.txt
meli_package-0.0.7.dist-info/RECORD
